arcane/bigquery_storage/__init__.py
arcane/bigquery_storage/client.py
arcane/bigquery_storage/proto/feed_boost_result.proto
arcane/bigquery_storage/proto/feed_boost_result_pb2.py
arcane/bigquery_storage/proto/feed_boost_result_pb2.pyi
arcane/bigquery_storage/proto/feed_boost_statistic.proto
arcane/bigquery_storage/proto/feed_boost_statistic_pb2.py
arcane/bigquery_storage/proto/feed_boost_statistic_pb2.pyi
arcane_bigquery_storage-1.2.0.dist-info/METADATA
arcane_bigquery_storage-1.2.0.dist-info/WHEEL
arcane_bigquery_storage-1.2.0.dist-info/RECORD
