Metadata-Version: 2.4
Name: arcane-bigquery-storage
Version: 1.2.0
Summary: A package to use the BigQuery Storage Write API
Author: Arcane
Author-email: product@wearcane.com
Requires-Python: >=3.9,<4.0
Classifier: Programming Language :: Python :: 3
Classifier: Programming Language :: Python :: 3.9
Classifier: Programming Language :: Python :: 3.10
Classifier: Programming Language :: Python :: 3.11
Classifier: Programming Language :: Python :: 3.12
Classifier: Programming Language :: Python :: 3.13
Classifier: Programming Language :: Python :: 3.14
Requires-Dist: backoff (>=1.10.0)
Requires-Dist: google-cloud-bigquery-storage (>=2.28.0,<3.0.0)
